MANIFEST.in
README.md
setup.py
q4nwin/__init__.py
q4nwin/toplevel.py
q4nwin.egg-info/PKG-INFO
q4nwin.egg-info/SOURCES.txt
q4nwin.egg-info/dependency_links.txt
q4nwin.egg-info/requires.txt
q4nwin.egg-info/top_level.txt
q4nwinext/__init__.py
q4nwinext/windbg_init.py
q4nwinext/pykd/__init__.py
q4nwinext/pykd/pykd.pyd
q4nwinlib/__init__.py
q4nwinlib/asm/__init__.py
q4nwinlib/context/__init__.py
q4nwinlib/dbg/__init__.py
q4nwinlib/interactive/__init__.py
q4nwinlib/interactive/win.py
q4nwinlib/interactive/winpwn.py
q4nwinlib/misc/__init__.py
q4nwinlib/misc/log.py