Metadata-Version: 2.1
Name: q4nwin
Version: 0.2.0
Summary: my windows pwntools
Home-page: https://github.com/Q4n/mywinpwn
Author: Q4n
Author-email: atq4n@qq.com
License: MIT Licence
Keywords: winpwn
Platform: Windows
Requires-Dist: six
